pmr2.client-0.2-py3.9-nspkg.pth
pmr2/client/__init__.py
pmr2/client/client.py
pmr2/client/script.py
pmr2.client-0.2.dist-info/METADATA
pmr2.client-0.2.dist-info/WHEEL
pmr2.client-0.2.dist-info/entry_points.txt
pmr2.client-0.2.dist-info/namespace_packages.txt
pmr2.client-0.2.dist-info/top_level.txt
pmr2.client-0.2.dist-info/RECORD
