Metadata-Version: 2.1
Name: pmr2.client
Version: 0.2
Summary: Client for PMR
Home-page: https://github.com/PMR/pmr2.client
Author: Tommy Yu
Author-email: tommy.yu@auckland.ac.nz
License: gpl
Platform: UNKNOWN
Classifier: Programming Language :: Python
Requires-Dist: setuptools
Requires-Dist: requests-oauthlib
